rich_style/__init__.py
rich_style/colors/character_color_map.py
rich_style/colors/color.py
rich_style/colors/gradient.py
rich_style/colors/parser/from_hsl.py
rich_style/colors/parser/from_html.py
rich_style/colors/parser/rainbow_text.py
rich_style/colors/parser/random_color.py
rich_style/colors/presets.py
rich_style/core/combine_text.py
rich_style/core/style.py
rich_style/enums.py
rich_style/styles/background.py
rich_style/styles/bold.py
rich_style/styles/bullet_list.py
rich_style/styles/foreground.py
rich_style/styles/italic.py
rich_style/styles/strikethrough.py
rich_style/styles/underline.py
rich_style/utils/prints/debug.py
rich_style/utils/prints/error.py
rich_style/utils/prints/info.py
rich_style/utils/prints/success.py
rich_style/utils/prints/timed.py
rich_style/utils/prints/warn.py
rich_style/utils/supports_ansi.py
rich_style-1.1.6.dist-info/METADATA
rich_style-1.1.6.dist-info/WHEEL
rich_style-1.1.6.dist-info/licenses/LICENSE
rich_style-1.1.6.dist-info/RECORD
